{
  "last_updated": "2026-06-17T19:28:32.170633+00:00",
  "total_jobs": 541,
  "live_count": 541,
  "retained_count": 0,
  "retention_hours": 10,
  "sources": {
    "Remotive": {
      "scanned": 30,
      "matched": 30
    },
    "WeWorkRemotely": {
      "scanned": 116,
      "matched": 116
    },
    "Arbeitnow": {
      "scanned": 100,
      "matched": 100
    },
    "Jobicy": {
      "scanned": 50,
      "matched": 50
    },
    "Working Nomads": {
      "scanned": 46,
      "matched": 46
    },
    "RemoteOK": {
      "scanned": 100,
      "matched": 100
    },
    "Himalayas": {
      "scanned": 100,
      "matched": 100
    },
    "Hacker News": {
      "scanned": 25,
      "matched": 25
    }
  }
}